{"level":"info","ts":"2023-03-24T05:38:12Z","logger":"setup","msg":"Starting CloudNativePG Instance Manager","logging_pod":"cluster-example-2","version":"1.19.1","build":{"Version":"1.19.1","Commit":"cb24d237","Date":"2023-03-20"}}
{"level":"info","ts":"2023-03-24T05:38:12Z","logger":"setup","msg":"starting controller-runtime manager","logging_pod":"cluster-example-2"}
{"level":"info","ts":"2023-03-24T05:38:12Z","msg":"Starting EventSource","controller":"cluster","controllerGroup":"postgresql.cnpg.io","controllerKind":"Cluster","source":"kind source: *v1.Cluster"}
{"level":"info","ts":"2023-03-24T05:38:12Z","msg":"Starting Controller","controller":"cluster","controllerGroup":"postgresql.cnpg.io","controllerKind":"Cluster"}
{"level":"debug","ts":"2023-03-24T05:38:12Z","msg":"starting the postgres loop","caller":"pkg/management/log/log.go:181","logging_pod":"cluster-example-2"}
{"level":"debug","ts":"2023-03-24T05:38:12Z","msg":"starting signal loop","caller":"pkg/management/log/log.go:181","logging_pod":"cluster-example-2"}
{"level":"debug","ts":"2023-03-24T05:38:12Z","msg":"Checking PGDATA coherence","caller":"internal/cmd/manager/instance/run/lifecycle/run.go:255","logging_pod":"cluster-example-2"}
{"level":"info","ts":"2023-03-24T05:38:12Z","msg":"Starting webserver","logging_pod":"cluster-example-2","address":":9187"}
{"level":"info","ts":"2023-03-24T05:38:12Z","msg":"Starting webserver","logging_pod":"cluster-example-2","address":":8000"}
{"level":"info","ts":"2023-03-24T05:38:12Z","msg":"Starting webserver","logging_pod":"cluster-example-2","address":"localhost:8010"}
{"level":"info","ts":"2023-03-24T05:38:12Z","msg":"Starting workers","controller":"cluster","controllerGroup":"postgresql.cnpg.io","controllerKind":"Cluster","worker count":1}
{"level":"debug","ts":"2023-03-24T05:38:12Z","msg":"Reconciling Cluster","controller":"cluster","controllerGroup":"postgresql.cnpg.io","controllerKind":"Cluster","Cluster":{"name":"cluster-example","namespace":"default"},"namespace":"default","name":"cluster-example","reconcileID":"8dd5d624-1027-4a5b-ac89-5ed3eb2f120f","uuid":"1128a65b-ca06-11ed-a0b0-da3b2ac0df1f","caller":"internal/management/controller/instance_controller.go:109","logging_pod":"cluster-example-2","cluster":{"apiVersion":"postgresql.cnpg.io/v1","kind":"Cluster","namespace":"default","name":"cluster-example"}}
{"level":"debug","ts":"2023-03-24T05:38:12Z","msg":"Reconciling custom monitoring queries","controller":"cluster","controllerGroup":"postgresql.cnpg.io","controllerKind":"Cluster","Cluster":{"name":"cluster-example","namespace":"default"},"namespace":"default","name":"cluster-example","reconcileID":"8dd5d624-1027-4a5b-ac89-5ed3eb2f120f","uuid":"1128a65b-ca06-11ed-a0b0-da3b2ac0df1f","caller":"internal/management/controller/instance_controller.go:727","logging_pod":"cluster-example-2"}
{"level":"info","ts":"2023-03-24T05:38:12Z","msg":"Refreshed configuration file","controller":"cluster","controllerGroup":"postgresql.cnpg.io","controllerKind":"Cluster","Cluster":{"name":"cluster-example","namespace":"default"},"namespace":"default","name":"cluster-example","reconcileID":"8dd5d624-1027-4a5b-ac89-5ed3eb2f120f","uuid":"1128a65b-ca06-11ed-a0b0-da3b2ac0df1f","logging_pod":"cluster-example-2","filename":"/controller/certificates/server.crt","secret":"cluster-example-server"}
{"level":"info","ts":"2023-03-24T05:38:12Z","msg":"Refreshed configuration file","controller":"cluster","controllerGroup":"postgresql.cnpg.io","controllerKind":"Cluster","Cluster":{"name":"cluster-example","namespace":"default"},"namespace":"default","name":"cluster-example","reconcileID":"8dd5d624-1027-4a5b-ac89-5ed3eb2f120f","uuid":"1128a65b-ca06-11ed-a0b0-da3b2ac0df1f","logging_pod":"cluster-example-2","filename":"/controller/certificates/server.key","secret":"cluster-example-server"}
{"level":"info","ts":"2023-03-24T05:38:12Z","msg":"Refreshed configuration file","controller":"cluster","controllerGroup":"postgresql.cnpg.io","controllerKind":"Cluster","Cluster":{"name":"cluster-example","namespace":"default"},"namespace":"default","name":"cluster-example","reconcileID":"8dd5d624-1027-4a5b-ac89-5ed3eb2f120f","uuid":"1128a65b-ca06-11ed-a0b0-da3b2ac0df1f","logging_pod":"cluster-example-2","filename":"/controller/certificates/streaming_replica.crt","secret":"cluster-example-replication"}
{"level":"info","ts":"2023-03-24T05:38:12Z","msg":"Refreshed configuration file","controller":"cluster","controllerGroup":"postgresql.cnpg.io","controllerKind":"Cluster","Cluster":{"name":"cluster-example","namespace":"default"},"namespace":"default","name":"cluster-example","reconcileID":"8dd5d624-1027-4a5b-ac89-5ed3eb2f120f","uuid":"1128a65b-ca06-11ed-a0b0-da3b2ac0df1f","logging_pod":"cluster-example-2","filename":"/controller/certificates/streaming_replica.key","secret":"cluster-example-replication"}
{"level":"info","ts":"2023-03-24T05:38:12Z","msg":"Refreshed configuration file","controller":"cluster","controllerGroup":"postgresql.cnpg.io","controllerKind":"Cluster","Cluster":{"name":"cluster-example","namespace":"default"},"namespace":"default","name":"cluster-example","reconcileID":"8dd5d624-1027-4a5b-ac89-5ed3eb2f120f","uuid":"1128a65b-ca06-11ed-a0b0-da3b2ac0df1f","logging_pod":"cluster-example-2","filename":"/controller/certificates/client-ca.crt","secret":"cluster-example-ca"}
{"level":"info","ts":"2023-03-24T05:38:12Z","msg":"Refreshed configuration file","controller":"cluster","controllerGroup":"postgresql.cnpg.io","controllerKind":"Cluster","Cluster":{"name":"cluster-example","namespace":"default"},"namespace":"default","name":"cluster-example","reconcileID":"8dd5d624-1027-4a5b-ac89-5ed3eb2f120f","uuid":"1128a65b-ca06-11ed-a0b0-da3b2ac0df1f","logging_pod":"cluster-example-2","filename":"/controller/certificates/server-ca.crt","secret":"cluster-example-ca"}
{"level":"info","ts":"2023-03-24T05:38:12Z","msg":"Cluster status","controller":"cluster","controllerGroup":"postgresql.cnpg.io","controllerKind":"Cluster","Cluster":{"name":"cluster-example","namespace":"default"},"namespace":"default","name":"cluster-example","reconcileID":"8dd5d624-1027-4a5b-ac89-5ed3eb2f120f","uuid":"1128a65b-ca06-11ed-a0b0-da3b2ac0df1f","logging_pod":"cluster-example-2","currentPrimary":"cluster-example-3","targetPrimary":"cluster-example-3"}
{"level":"info","ts":"2023-03-24T05:38:12Z","msg":"This is an old primary instance, waiting for the switchover to finish","controller":"cluster","controllerGroup":"postgresql.cnpg.io","controllerKind":"Cluster","Cluster":{"name":"cluster-example","namespace":"default"},"namespace":"default","name":"cluster-example","reconcileID":"8dd5d624-1027-4a5b-ac89-5ed3eb2f120f","uuid":"1128a65b-ca06-11ed-a0b0-da3b2ac0df1f","logging_pod":"cluster-example-2","currentPrimary":"cluster-example-3","targetPrimary":"cluster-example-3"}
{"level":"info","ts":"2023-03-24T05:38:12Z","msg":"Switchover completed","controller":"cluster","controllerGroup":"postgresql.cnpg.io","controllerKind":"Cluster","Cluster":{"name":"cluster-example","namespace":"default"},"namespace":"default","name":"cluster-example","reconcileID":"8dd5d624-1027-4a5b-ac89-5ed3eb2f120f","uuid":"1128a65b-ca06-11ed-a0b0-da3b2ac0df1f","logging_pod":"cluster-example-2","targetPrimary":"cluster-example-3","currentPrimary":"cluster-example-3"}
{"level":"info","ts":"2023-03-24T05:38:12Z","msg":"Waiting for the new primary to be available","logging_pod":"cluster-example-2","primaryConnInfo":"host=cluster-example-rw user=streaming_replica port=5432 sslkey=/controller/certificates/streaming_replica.key sslcert=/controller/certificates/streaming_replica.crt sslrootcert=/controller/certificates/server-ca.crt application_name=cluster-example-2 sslmode=verify-ca dbname=postgres connect_timeout=5"}
{"level":"info","ts":"2023-03-24T05:38:12Z","msg":"Extracting pg_controldata information","logging_pod":"cluster-example-2","reason":"before pg_rewind"}
{"level":"info","ts":"2023-03-24T05:38:12Z","msg":"Readiness probe failing","logging_pod":"cluster-example-2","err":"instance is not ready yet"}
{"level":"info","ts":"2023-03-24T05:38:12Z","logger":"pg_controldata","msg":"pg_control version number:            1300\nCatalog version number:               202209061\nDatabase system identifier:           7213723966086483989\nDatabase cluster state:               shut down\npg_control last modified:             Fri 24 Mar 2023 05:27:59 AM UTC\nLatest checkpoint location:           0/10000028\nLatest checkpoint's REDO location:    0/10000028\nLatest checkpoint's REDO WAL file:    000000040000000000000010\nLatest checkpoint's TimeLineID:       4\nLatest checkpoint's PrevTimeLineID:   4\nLatest checkpoint's full_page_writes: on\nLatest checkpoint's NextXID:          0:744\nLatest checkpoint's NextOID:          24578\nLatest checkpoint's NextMultiXactId:  1\nLatest checkpoint's NextMultiOffset:  0\nLatest checkpoint's oldestXID:        716\nLatest checkpoint's oldestXID's DB:   1\nLatest checkpoint's oldestActiveXID:  0\nLatest checkpoint's oldestMultiXid:   1\nLatest checkpoint's oldestMulti's DB: 1\nLatest checkpoint's oldestCommitTsXid:0\nLatest checkpoint's newestCommitTsXid:0\nTime of latest checkpoint:            Fri 24 Mar 2023 05:27:58 AM UTC\nFake LSN counter for unlogged rels:   0/3E8\nMinimum recovery ending location:     0/0\nMin recovery ending loc's timeline:   0\nBackup start location:                0/0\nBackup end location:                  0/0\nEnd-of-backup record required:        no\nwal_level setting:                    logical\nwal_log_hints setting:                on\nmax_connections setting:              100\nmax_worker_processes setting:         32\nmax_wal_senders setting:              10\nmax_prepared_xacts setting:           0\nmax_locks_per_xact setting:           64\ntrack_commit_timestamp setting:       off\nMaximum data alignment:               8\nDatabase block size:                  8192\nBlocks per segment of large relation: 131072\nWAL block size:                       8192\nBytes per WAL segment:                16777216\nMaximum length of identifiers:        64\nMaximum columns in an index:          32\nMaximum size of a TOAST chunk:        1996\nSize of a large-object chunk:         2048\nDate/time type storage:               64-bit integers\nFloat8 argument passing:              by value\nData page checksum version:           0\nMock authentication nonce:            b7f2f04197c763627732f064e0e1fca36c334973d9441ff8e49c207f6cd5a38f\n","pipe":"stdout","logging_pod":"cluster-example-2"}
{"level":"info","ts":"2023-03-24T05:38:12Z","msg":"Starting up pg_rewind","logging_pod":"cluster-example-2","pgdata":"/var/lib/postgresql/data/pgdata","options":["-P","--source-server","host=cluster-example-rw user=streaming_replica port=5432 sslkey=/controller/certificates/streaming_replica.key sslcert=/controller/certificates/streaming_replica.crt sslrootcert=/controller/certificates/server-ca.crt application_name=cluster-example-2 sslmode=verify-ca dbname=postgres","--target-pgdata","/var/lib/postgresql/data/pgdata","--restore-target-wal"]}
{"level":"info","ts":"2023-03-24T05:38:13Z","msg":"Readiness probe failing","logging_pod":"cluster-example-2","err":"instance is not ready yet"}
{"level":"info","ts":"2023-03-24T05:38:14Z","msg":"Readiness probe failing","logging_pod":"cluster-example-2","err":"instance is not ready yet"}
TODO: {"level":"info","ts":"2023-03-24T05:38:15Z","logger":"pg_rewind","msg":"pg_rewind: connected to server","pipe":"stderr","logging_pod":"cluster-example-2"}
TODO: {"level":"info","ts":"2023-03-24T05:38:15Z","logger":"pg_rewind","msg":"pg_rewind: servers diverged at WAL location 0/F000060 on timeline 4","pipe":"stderr","logging_pod":"cluster-example-2"}
TODO: {"level":"info","ts":"2023-03-24T05:38:15Z","logger":"pg_rewind","msg":"pg_rewind: rewinding from last common checkpoint at 0/E000098 on timeline 4","pipe":"stderr","logging_pod":"cluster-example-2"}
TODO: {"level":"info","ts":"2023-03-24T05:38:15Z","logger":"pg_rewind","msg":"pg_rewind: reading source file list","pipe":"stderr","logging_pod":"cluster-example-2"}
TODO: {"level":"info","ts":"2023-03-24T05:38:19Z","logger":"pg_rewind","msg":"pg_rewind: reading target file list","pipe":"stderr","logging_pod":"cluster-example-2"}
TODO: {"level":"info","ts":"2023-03-24T05:38:19Z","logger":"pg_rewind","msg":"pg_rewind: reading WAL in target","pipe":"stderr","logging_pod":"cluster-example-2"}
TODO: {"level":"info","ts":"2023-03-24T05:38:19Z","logger":"pg_rewind","msg":"pg_rewind: need to copy 84 MB (total source directory size is 109 MB)","pipe":"stderr","logging_pod":"cluster-example-2"}
TODO: {"level":"info","ts":"2023-03-24T05:38:19Z","logger":"pg_rewind","msg":"    0/86873 kB (0%) copied","pipe":"stderr","logging_pod":"cluster-example-2"}
TODO: {"level":"info","ts":"2023-03-24T05:38:20Z","logger":"pg_rewind","msg":"13108/86873 kB (15%) copied","pipe":"stderr","logging_pod":"cluster-example-2"}
TODO: {"level":"info","ts":"2023-03-24T05:38:20Z","msg":"Readiness probe failing","logging_pod":"cluster-example-2","err":"instance is not ready yet"}
TODO: {"level":"info","ts":"2023-03-24T05:38:21Z","logger":"pg_rewind","msg":"pg_rewind: error: unexpected result while fetching remote files: server closed the connection unexpectedly","pipe":"stderr","logging_pod":"cluster-example-2"}
TODO: {"level":"info","ts":"2023-03-24T05:38:21Z","logger":"pg_rewind","msg":"\tThis probably means the server terminated abnormally","pipe":"stderr","logging_pod":"cluster-example-2"}
TODO: {"level":"info","ts":"2023-03-24T05:38:21Z","logger":"pg_rewind","msg":"\tbefore or while processing the request.","pipe":"stderr","logging_pod":"cluster-example-2"}
TODO: {"level":"info","ts":"2023-03-24T05:38:21Z","logger":"pg_rewind","msg":"server closed the connection unexpectedly","pipe":"stderr","logging_pod":"cluster-example-2"}
TODO: {"level":"info","ts":"2023-03-24T05:38:21Z","logger":"pg_rewind","msg":"\tThis probably means the server terminated abnormally","pipe":"stderr","logging_pod":"cluster-example-2"}
TODO: {"level":"info","ts":"2023-03-24T05:38:21Z","logger":"pg_rewind","msg":"\tbefore or while processing the request.","pipe":"stderr","logging_pod":"cluster-example-2"}
TODO: {"level":"error","ts":"2023-03-24T05:38:21Z","msg":"Failed to execute pg_rewind","logging_pod":"cluster-example-2","options":["-P","--source-server","host=cluster-example-rw user=streaming_replica port=5432 sslkey=/controller/certificates/streaming_replica.key sslcert=/controller/certificates/streaming_replica.crt sslrootcert=/controller/certificates/server-ca.crt application_name=cluster-example-2 sslmode=verify-ca dbname=postgres","--target-pgdata","/var/lib/postgresql/data/pgdata","--restore-target-wal"],"error":"exit status 1","stacktrace":"github.com/cloudnative-pg/cloudnative-pg/pkg/management/log.(*logger).Error\n\tpkg/management/log/log.go:128\ngithub.com/cloudnative-pg/cloudnative-pg/pkg/management/log.Error\n\tpkg/management/log/log.go:166\ngithub.com/cloudnative-pg/cloudnative-pg/pkg/management/postgres.(*Instance).Rewind\n\tpkg/management/postgres/instance.go:783\ngithub.com/cloudnative-pg/cloudnative-pg/internal/management/controller.(*InstanceReconciler).verifyPgDataCoherenceForPrimary\n\tinternal/management/controller/instance_startup.go:235\ngithub.com/cloudnative-pg/cloudnative-pg/internal/management/controller.(*InstanceReconciler).initialize\n\tinternal/management/controller/instance_controller.go:327\ngithub.com/cloudnative-pg/cloudnative-pg/internal/management/controller.(*InstanceReconciler).Reconcile\n\tinternal/management/controller/instance_controller.go:141\nsigs.k8s.io/controller-runtime/pkg/internal/controller.(*Controller).Reconcile\n\tpkg/mod/sigs.k8s.io/controller-runtime@v0.14.5/pkg/internal/controller/controller.go:122\nsigs.k8s.io/controller-runtime/pkg/internal/controller.(*Controller).reconcileHandler\n\tpkg/mod/sigs.k8s.io/controller-runtime@v0.14.5/pkg/internal/controller/controller.go:323\nsigs.k8s.io/controller-runtime/pkg/internal/controller.(*Controller).processNextWorkItem\n\tpkg/mod/sigs.k8s.io/controller-runtime@v0.14.5/pkg/internal/controller/controller.go:274\nsigs.k8s.io/controller-runtime/pkg/internal/controller.(*Controller).Start.func2.2\n\tpkg/mod/sigs.k8s.io/controller-runtime@v0.14.5/pkg/internal/controller/controller.go:235"}
{"level":"info","ts":"2023-03-24T05:38:21Z","msg":"pg_rewind failed, starting the server to complete the crash recovery","controller":"cluster","controllerGroup":"postgresql.cnpg.io","controllerKind":"Cluster","Cluster":{"name":"cluster-example","namespace":"default"},"namespace":"default","name":"cluster-example","reconcileID":"8dd5d624-1027-4a5b-ac89-5ed3eb2f120f","uuid":"1128a65b-ca06-11ed-a0b0-da3b2ac0df1f","logging_pod":"cluster-example-2","err":"error executing pg_rewind: exit status 1"}
{"level":"info","ts":"2023-03-24T05:38:21Z","msg":"Waiting for server to complete crash recovery","logging_pod":"cluster-example-2"}
{"level":"info","ts":"2023-03-24T05:38:21Z","msg":"Starting up instance","logging_pod":"cluster-example-2","pgdata":"/var/lib/postgresql/data/pgdata","options":["start","-w","-D","/var/lib/postgresql/data/pgdata","-o","-c port=5432 -c unix_socket_directories=/controller/run","-t 40000000"]}
{"level":"info","ts":"2023-03-24T05:38:21Z","logger":"pg_ctl","msg":"waiting for server to start....2023-03-24 05:38:21.165 GMT [26] LOG:  starting PostgreSQL 15.2 (Debian 15.2-1.pgdg110+1) on x86_64-pc-linux-gnu, compiled by gcc (Debian 10.2.1-6) 10.2.1 20210110, 64-bit","pipe":"stdout","logging_pod":"cluster-example-2"}
{"level":"info","ts":"2023-03-24T05:38:21Z","logger":"pg_ctl","msg":"2023-03-24 05:38:21.168 GMT [26] LOG:  listening on IPv6 address \"::1\", port 5432","pipe":"stdout","logging_pod":"cluster-example-2"}
{"level":"info","ts":"2023-03-24T05:38:21Z","logger":"pg_ctl","msg":"2023-03-24 05:38:21.168 GMT [26] LOG:  listening on IPv4 address \"127.0.0.1\", port 5432","pipe":"stdout","logging_pod":"cluster-example-2"}
{"level":"info","ts":"2023-03-24T05:38:21Z","logger":"pg_ctl","msg":"2023-03-24 05:38:21.175 GMT [26] LOG:  listening on Unix socket \"/controller/run/.s.PGSQL.5432\"","pipe":"stdout","logging_pod":"cluster-example-2"}
{"level":"info","ts":"2023-03-24T05:38:21Z","logger":"pg_ctl","msg":"2023-03-24 05:38:21.179 GMT [26] LOG:  hostssl record cannot match because SSL is disabled","pipe":"stdout","logging_pod":"cluster-example-2"}
{"level":"info","ts":"2023-03-24T05:38:21Z","logger":"pg_ctl","msg":"2023-03-24 05:38:21.179 GMT [26] HINT:  Set ssl = on in postgresql.conf.","pipe":"stdout","logging_pod":"cluster-example-2"}
{"level":"info","ts":"2023-03-24T05:38:21Z","logger":"pg_ctl","msg":"2023-03-24 05:38:21.179 GMT [26] CONTEXT:  line 6 of configuration file \"/var/lib/postgresql/data/pgdata/pg_hba.conf\"","pipe":"stdout","logging_pod":"cluster-example-2"}
{"level":"info","ts":"2023-03-24T05:38:21Z","logger":"pg_ctl","msg":"2023-03-24 05:38:21.179 GMT [26] LOG:  hostssl record cannot match because SSL is disabled","pipe":"stdout","logging_pod":"cluster-example-2"}
{"level":"info","ts":"2023-03-24T05:38:21Z","logger":"pg_ctl","msg":"2023-03-24 05:38:21.179 GMT [26] HINT:  Set ssl = on in postgresql.conf.","pipe":"stdout","logging_pod":"cluster-example-2"}
{"level":"info","ts":"2023-03-24T05:38:21Z","logger":"pg_ctl","msg":"2023-03-24 05:38:21.179 GMT [26] CONTEXT:  line 7 of configuration file \"/var/lib/postgresql/data/pgdata/pg_hba.conf\"","pipe":"stdout","logging_pod":"cluster-example-2"}
{"level":"info","ts":"2023-03-24T05:38:21Z","logger":"pg_ctl","msg":"2023-03-24 05:38:21.179 GMT [26] LOG:  hostssl record cannot match because SSL is disabled","pipe":"stdout","logging_pod":"cluster-example-2"}
{"level":"info","ts":"2023-03-24T05:38:21Z","logger":"pg_ctl","msg":"2023-03-24 05:38:21.179 GMT [26] HINT:  Set ssl = on in postgresql.conf.","pipe":"stdout","logging_pod":"cluster-example-2"}
{"level":"info","ts":"2023-03-24T05:38:21Z","logger":"pg_ctl","msg":"2023-03-24 05:38:21.179 GMT [26] CONTEXT:  line 8 of configuration file \"/var/lib/postgresql/data/pgdata/pg_hba.conf\"","pipe":"stdout","logging_pod":"cluster-example-2"}
{"level":"info","ts":"2023-03-24T05:38:21Z","logger":"pg_ctl","msg":"2023-03-24 05:38:21.186 GMT [29] LOG:  database system was shut down at 2023-03-24 05:27:59 GMT","pipe":"stdout","logging_pod":"cluster-example-2"}
{"level":"info","ts":"2023-03-24T05:38:21Z","logger":"pg_ctl","msg":"2023-03-24 05:38:21.186 GMT [29] LOG:  invalid primary checkpoint record","pipe":"stdout","logging_pod":"cluster-example-2"}
{"level":"info","ts":"2023-03-24T05:38:21Z","logger":"pg_ctl","msg":"2023-03-24 05:38:21.186 GMT [29] PANIC:  could not locate a valid checkpoint record","pipe":"stdout","logging_pod":"cluster-example-2"}
{"level":"info","ts":"2023-03-24T05:38:21Z","logger":"pg_ctl","msg":"2023-03-24 05:38:21.384 GMT [26] LOG:  startup process (PID 29) was terminated by signal 6: Aborted","pipe":"stdout","logging_pod":"cluster-example-2"}
{"level":"info","ts":"2023-03-24T05:38:21Z","logger":"pg_ctl","msg":"2023-03-24 05:38:21.384 GMT [26] LOG:  aborting startup due to startup process failure","pipe":"stdout","logging_pod":"cluster-example-2"}
{"level":"info","ts":"2023-03-24T05:38:21Z","logger":"pg_ctl","msg":"2023-03-24 05:38:21.385 GMT [26] LOG:  database system is shut down","pipe":"stdout","logging_pod":"cluster-example-2"}
{"level":"info","ts":"2023-03-24T05:38:21Z","logger":"pg_ctl","msg":"pg_ctl: could not start server","pipe":"stderr","logging_pod":"cluster-example-2"}
{"level":"info","ts":"2023-03-24T05:38:21Z","logger":"pg_ctl","msg":"Examine the log output.","pipe":"stderr","logging_pod":"cluster-example-2"}
{"level":"info","ts":"2023-03-24T05:38:21Z","logger":"pg_ctl","msg":" stopped waiting","pipe":"stdout","logging_pod":"cluster-example-2"}
{"level":"info","ts":"2023-03-24T05:38:21Z","msg":"Exited log pipe","fileName":"/controller/log/postgres.csv","logging_pod":"cluster-example-2"}
{"level":"error","ts":"2023-03-24T05:38:21Z","msg":"Reconciler error","controller":"cluster","controllerGroup":"postgresql.cnpg.io","controllerKind":"Cluster","Cluster":{"name":"cluster-example","namespace":"default"},"namespace":"default","name":"cluster-example","reconcileID":"8dd5d624-1027-4a5b-ac89-5ed3eb2f120f","error":"while activating instance: error starting PostgreSQL instance: exit status 1","stacktrace":"sigs.k8s.io/controller-runtime/pkg/internal/controller.(*Controller).reconcileHandler\n\tpkg/mod/sigs.k8s.io/controller-runtime@v0.14.5/pkg/internal/controller/controller.go:329\nsigs.k8s.io/controller-runtime/pkg/internal/controller.(*Controller).processNextWorkItem\n\tpkg/mod/sigs.k8s.io/controller-runtime@v0.14.5/pkg/internal/controller/controller.go:274\nsigs.k8s.io/controller-runtime/pkg/internal/controller.(*Controller).Start.func2.2\n\tpkg/mod/sigs.k8s.io/controller-runtime@v0.14.5/pkg/internal/controller/controller.go:235"}
{"level":"debug","ts":"2023-03-24T05:38:21Z","msg":"Reconciling Cluster","controller":"cluster","controllerGroup":"postgresql.cnpg.io","controllerKind":"Cluster","Cluster":{"name":"cluster-example","namespace":"default"},"namespace":"default","name":"cluster-example","reconcileID":"9f60a535-8cb8-4bf6-8ecb-da0a776eee8c","uuid":"167d3925-ca06-11ed-a0b0-da3b2ac0df1f","caller":"internal/management/controller/instance_controller.go:109","logging_pod":"cluster-example-2","cluster":{"apiVersion":"postgresql.cnpg.io/v1","kind":"Cluster","namespace":"default","name":"cluster-example"}}
{"level":"debug","ts":"2023-03-24T05:38:21Z","msg":"Reconciling custom monitoring queries","controller":"cluster","controllerGroup":"postgresql.cnpg.io","controllerKind":"Cluster","Cluster":{"name":"cluster-example","namespace":"default"},"namespace":"default","name":"cluster-example","reconcileID":"9f60a535-8cb8-4bf6-8ecb-da0a776eee8c","uuid":"167d3925-ca06-11ed-a0b0-da3b2ac0df1f","caller":"internal/management/controller/instance_controller.go:727","logging_pod":"cluster-example-2"}
{"level":"info","ts":"2023-03-24T05:38:21Z","msg":"Cluster status","controller":"cluster","controllerGroup":"postgresql.cnpg.io","controllerKind":"Cluster","Cluster":{"name":"cluster-example","namespace":"default"},"namespace":"default","name":"cluster-example","reconcileID":"9f60a535-8cb8-4bf6-8ecb-da0a776eee8c","uuid":"167d3925-ca06-11ed-a0b0-da3b2ac0df1f","logging_pod":"cluster-example-2","currentPrimary":"cluster-example-3","targetPrimary":"cluster-example-3"}
{"level":"info","ts":"2023-03-24T05:38:21Z","msg":"This is an old primary instance, waiting for the switchover to finish","controller":"cluster","controllerGroup":"postgresql.cnpg.io","controllerKind":"Cluster","Cluster":{"name":"cluster-example","namespace":"default"},"namespace":"default","name":"cluster-example","reconcileID":"9f60a535-8cb8-4bf6-8ecb-da0a776eee8c","uuid":"167d3925-ca06-11ed-a0b0-da3b2ac0df1f","logging_pod":"cluster-example-2","currentPrimary":"cluster-example-3","targetPrimary":"cluster-example-3"}
{"level":"info","ts":"2023-03-24T05:38:21Z","msg":"Switchover completed","controller":"cluster","controllerGroup":"postgresql.cnpg.io","controllerKind":"Cluster","Cluster":{"name":"cluster-example","namespace":"default"},"namespace":"default","name":"cluster-example","reconcileID":"9f60a535-8cb8-4bf6-8ecb-da0a776eee8c","uuid":"167d3925-ca06-11ed-a0b0-da3b2ac0df1f","logging_pod":"cluster-example-2","targetPrimary":"cluster-example-3","currentPrimary":"cluster-example-3"}
{"level":"info","ts":"2023-03-24T05:38:21Z","msg":"Waiting for the new primary to be available","logging_pod":"cluster-example-2","primaryConnInfo":"host=cluster-example-rw user=streaming_replica port=5432 sslkey=/controller/certificates/streaming_replica.key sslcert=/controller/certificates/streaming_replica.crt sslrootcert=/controller/certificates/server-ca.crt application_name=cluster-example-2 sslmode=verify-ca dbname=postgres connect_timeout=5"}
{"level":"info","ts":"2023-03-24T05:38:21Z","msg":"Extracting pg_controldata information","logging_pod":"cluster-example-2","reason":"before pg_rewind"}
{"level":"info","ts":"2023-03-24T05:38:21Z","logger":"pg_controldata","msg":"pg_control version number:            1300\nCatalog version number:               202209061\nDatabase system identifier:           7213723966086483989\nDatabase cluster state:               shut down\npg_control last modified:             Fri 24 Mar 2023 05:27:59 AM UTC\nLatest checkpoint location:           0/10000028\nLatest checkpoint's REDO location:    0/10000028\nLatest checkpoint's REDO WAL file:    000000040000000000000010\nLatest checkpoint's TimeLineID:       4\nLatest checkpoint's PrevTimeLineID:   4\nLatest checkpoint's full_page_writes: on\nLatest checkpoint's NextXID:          0:744\nLatest checkpoint's NextOID:          24578\nLatest checkpoint's NextMultiXactId:  1\nLatest checkpoint's NextMultiOffset:  0\nLatest checkpoint's oldestXID:        716\nLatest checkpoint's oldestXID's DB:   1\nLatest checkpoint's oldestActiveXID:  0\nLatest checkpoint's oldestMultiXid:   1\nLatest checkpoint's oldestMulti's DB: 1\nLatest checkpoint's oldestCommitTsXid:0\nLatest checkpoint's newestCommitTsXid:0\nTime of latest checkpoint:            Fri 24 Mar 2023 05:27:58 AM UTC\nFake LSN counter for unlogged rels:   0/3E8\nMinimum recovery ending location:     0/0\nMin recovery ending loc's timeline:   0\nBackup start location:                0/0\nBackup end location:                  0/0\nEnd-of-backup record required:        no\nwal_level setting:                    logical\nwal_log_hints setting:                on\nmax_connections setting:              100\nmax_worker_processes setting:         32\nmax_wal_senders setting:              10\nmax_prepared_xacts setting:           0\nmax_locks_per_xact setting:           64\ntrack_commit_timestamp setting:       off\nMaximum data alignment:               8\nDatabase block size:                  8192\nBlocks per segment of large relation: 131072\nWAL block size:                       8192\nBytes per WAL segment:                16777216\nMaximum length of identifiers:        64\nMaximum columns in an index:          32\nMaximum size of a TOAST chunk:        1996\nSize of a large-object chunk:         2048\nDate/time type storage:               64-bit integers\nFloat8 argument passing:              by value\nData page checksum version:           0\nMock authentication nonce:            b7f2f04197c763627732f064e0e1fca36c334973d9441ff8e49c207f6cd5a38f\n","pipe":"stdout","logging_pod":"cluster-example-2"}
{"level":"info","ts":"2023-03-24T05:38:21Z","msg":"Starting up pg_rewind","logging_pod":"cluster-example-2","pgdata":"/var/lib/postgresql/data/pgdata","options":["-P","--source-server","host=cluster-example-rw user=streaming_replica port=5432 sslkey=/controller/certificates/streaming_replica.key sslcert=/controller/certificates/streaming_replica.crt sslrootcert=/controller/certificates/server-ca.crt application_name=cluster-example-2 sslmode=verify-ca dbname=postgres","--target-pgdata","/var/lib/postgresql/data/pgdata","--restore-target-wal"]}
{"level":"info","ts":"2023-03-24T05:38:21Z","logger":"pg_rewind","msg":"pg_rewind: error: restore_command is not set in the target cluster","pipe":"stderr","logging_pod":"cluster-example-2"}
{"level":"error","ts":"2023-03-24T05:38:21Z","msg":"Failed to execute pg_rewind","logging_pod":"cluster-example-2","options":["-P","--source-server","host=cluster-example-rw user=streaming_replica port=5432 sslkey=/controller/certificates/streaming_replica.key sslcert=/controller/certificates/streaming_replica.crt sslrootcert=/controller/certificates/server-ca.crt application_name=cluster-example-2 sslmode=verify-ca dbname=postgres","--target-pgdata","/var/lib/postgresql/data/pgdata","--restore-target-wal"],"error":"exit status 1","stacktrace":"github.com/cloudnative-pg/cloudnative-pg/pkg/management/log.(*logger).Error\n\tpkg/management/log/log.go:128\ngithub.com/cloudnative-pg/cloudnative-pg/pkg/management/log.Error\n\tpkg/management/log/log.go:166\ngithub.com/cloudnative-pg/cloudnative-pg/pkg/management/postgres.(*Instance).Rewind\n\tpkg/management/postgres/instance.go:783\ngithub.com/cloudnative-pg/cloudnative-pg/internal/management/controller.(*InstanceReconciler).verifyPgDataCoherenceForPrimary\n\tinternal/management/controller/instance_startup.go:235\ngithub.com/cloudnative-pg/cloudnative-pg/internal/management/controller.(*InstanceReconciler).initialize\n\tinternal/management/controller/instance_controller.go:327\ngithub.com/cloudnative-pg/cloudnative-pg/internal/management/controller.(*InstanceReconciler).Reconcile\n\tinternal/management/controller/instance_controller.go:141\nsigs.k8s.io/controller-runtime/pkg/internal/controller.(*Controller).Reconcile\n\tpkg/mod/sigs.k8s.io/controller-runtime@v0.14.5/pkg/internal/controller/controller.go:122\nsigs.k8s.io/controller-runtime/pkg/internal/controller.(*Controller).reconcileHandler\n\tpkg/mod/sigs.k8s.io/controller-runtime@v0.14.5/pkg/internal/controller/controller.go:323\nsigs.k8s.io/controller-runtime/pkg/internal/controller.(*Controller).processNextWorkItem\n\tpkg/mod/sigs.k8s.io/controller-runtime@v0.14.5/pkg/internal/controller/controller.go:274\nsigs.k8s.io/controller-runtime/pkg/internal/controller.(*Controller).Start.func2.2\n\tpkg/mod/sigs.k8s.io/controller-runtime@v0.14.5/pkg/internal/controller/controller.go:235"}
{"level":"info","ts":"2023-03-24T05:38:21Z","msg":"pg_rewind failed, starting the server to complete the crash recovery","controller":"cluster","controllerGroup":"postgresql.cnpg.io","controllerKind":"Cluster","Cluster":{"name":"cluster-example","namespace":"default"},"namespace":"default","name":"cluster-example","reconcileID":"9f60a535-8cb8-4bf6-8ecb-da0a776eee8c","uuid":"167d3925-ca06-11ed-a0b0-da3b2ac0df1f","logging_pod":"cluster-example-2","err":"error executing pg_rewind: exit status 1"}
{"level":"info","ts":"2023-03-24T05:38:21Z","msg":"Waiting for server to complete crash recovery","logging_pod":"cluster-example-2"}
{"level":"info","ts":"2023-03-24T05:38:21Z","msg":"Starting up instance","logging_pod":"cluster-example-2","pgdata":"/var/lib/postgresql/data/pgdata","options":["start","-w","-D","/var/lib/postgresql/data/pgdata","-o","-c port=5432 -c unix_socket_directories=/controller/run","-t 40000000"]}
{"level":"info","ts":"2023-03-24T05:38:21Z","logger":"pg_ctl","msg":"waiting for server to start....2023-03-24 05:38:21.546 GMT [41] LOG:  starting PostgreSQL 15.2 (Debian 15.2-1.pgdg110+1) on x86_64-pc-linux-gnu, compiled by gcc (Debian 10.2.1-6) 10.2.1 20210110, 64-bit","pipe":"stdout","logging_pod":"cluster-example-2"}
{"level":"info","ts":"2023-03-24T05:38:21Z","logger":"pg_ctl","msg":"2023-03-24 05:38:21.546 GMT [41] LOG:  listening on IPv6 address \"::1\", port 5432","pipe":"stdout","logging_pod":"cluster-example-2"}
{"level":"info","ts":"2023-03-24T05:38:21Z","logger":"pg_ctl","msg":"2023-03-24 05:38:21.546 GMT [41] LOG:  listening on IPv4 address \"127.0.0.1\", port 5432","pipe":"stdout","logging_pod":"cluster-example-2"}
{"level":"info","ts":"2023-03-24T05:38:21Z","logger":"pg_ctl","msg":"2023-03-24 05:38:21.553 GMT [41] LOG:  listening on Unix socket \"/controller/run/.s.PGSQL.5432\"","pipe":"stdout","logging_pod":"cluster-example-2"}
{"level":"info","ts":"2023-03-24T05:38:21Z","logger":"pg_ctl","msg":"2023-03-24 05:38:21.560 GMT [41] LOG:  hostssl record cannot match because SSL is disabled","pipe":"stdout","logging_pod":"cluster-example-2"}
{"level":"info","ts":"2023-03-24T05:38:21Z","logger":"pg_ctl","msg":"2023-03-24 05:38:21.560 GMT [41] HINT:  Set ssl = on in postgresql.conf.","pipe":"stdout","logging_pod":"cluster-example-2"}
{"level":"info","ts":"2023-03-24T05:38:21Z","logger":"pg_ctl","msg":"2023-03-24 05:38:21.560 GMT [41] CONTEXT:  line 6 of configuration file \"/var/lib/postgresql/data/pgdata/pg_hba.conf\"","pipe":"stdout","logging_pod":"cluster-example-2"}
{"level":"info","ts":"2023-03-24T05:38:21Z","logger":"pg_ctl","msg":"2023-03-24 05:38:21.560 GMT [41] LOG:  hostssl record cannot match because SSL is disabled","pipe":"stdout","logging_pod":"cluster-example-2"}
{"level":"info","ts":"2023-03-24T05:38:21Z","logger":"pg_ctl","msg":"2023-03-24 05:38:21.560 GMT [41] HINT:  Set ssl = on in postgresql.conf.","pipe":"stdout","logging_pod":"cluster-example-2"}
{"level":"info","ts":"2023-03-24T05:38:21Z","logger":"pg_ctl","msg":"2023-03-24 05:38:21.560 GMT [41] CONTEXT:  line 7 of configuration file \"/var/lib/postgresql/data/pgdata/pg_hba.conf\"","pipe":"stdout","logging_pod":"cluster-example-2"}
{"level":"info","ts":"2023-03-24T05:38:21Z","logger":"pg_ctl","msg":"2023-03-24 05:38:21.560 GMT [41] LOG:  hostssl record cannot match because SSL is disabled","pipe":"stdout","logging_pod":"cluster-example-2"}
{"level":"info","ts":"2023-03-24T05:38:21Z","logger":"pg_ctl","msg":"2023-03-24 05:38:21.560 GMT [41] HINT:  Set ssl = on in postgresql.conf.","pipe":"stdout","logging_pod":"cluster-example-2"}
{"level":"info","ts":"2023-03-24T05:38:21Z","logger":"pg_ctl","msg":"2023-03-24 05:38:21.560 GMT [41] CONTEXT:  line 8 of configuration file \"/var/lib/postgresql/data/pgdata/pg_hba.conf\"","pipe":"stdout","logging_pod":"cluster-example-2"}
{"level":"info","ts":"2023-03-24T05:38:21Z","logger":"pg_ctl","msg":"2023-03-24 05:38:21.569 GMT [44] LOG:  database system was shut down at 2023-03-24 05:27:59 GMT","pipe":"stdout","logging_pod":"cluster-example-2"}
{"level":"info","ts":"2023-03-24T05:38:21Z","logger":"pg_ctl","msg":"2023-03-24 05:38:21.569 GMT [44] LOG:  invalid primary checkpoint record","pipe":"stdout","logging_pod":"cluster-example-2"}
{"level":"info","ts":"2023-03-24T05:38:21Z","logger":"pg_ctl","msg":"2023-03-24 05:38:21.569 GMT [44] PANIC:  could not locate a valid checkpoint record","pipe":"stdout","logging_pod":"cluster-example-2"}
{"level":"info","ts":"2023-03-24T05:38:21Z","logger":"pg_ctl","msg":"2023-03-24 05:38:21.686 GMT [41] LOG:  startup process (PID 44) was terminated by signal 6: Aborted","pipe":"stdout","logging_pod":"cluster-example-2"}
{"level":"info","ts":"2023-03-24T05:38:21Z","logger":"pg_ctl","msg":"2023-03-24 05:38:21.686 GMT [41] LOG:  aborting startup due to startup process failure","pipe":"stdout","logging_pod":"cluster-example-2"}
{"level":"info","ts":"2023-03-24T05:38:21Z","logger":"pg_ctl","msg":"2023-03-24 05:38:21.687 GMT [41] LOG:  database system is shut down","pipe":"stdout","logging_pod":"cluster-example-2"}
{"level":"info","ts":"2023-03-24T05:38:21Z","logger":"pg_ctl","msg":"pg_ctl: could not start server","pipe":"stderr","logging_pod":"cluster-example-2"}
{"level":"info","ts":"2023-03-24T05:38:21Z","logger":"pg_ctl","msg":"Examine the log output.","pipe":"stderr","logging_pod":"cluster-example-2"}
{"level":"info","ts":"2023-03-24T05:38:21Z","logger":"pg_ctl","msg":" stopped waiting","pipe":"stdout","logging_pod":"cluster-example-2"}
